Metadata-Version: 2.1
Name: mcStalker
Version: 0.1.3
Summary: mcStalker is an Asynchronous API Wrapper for the MCStalker (https://mcstalker.com) API. It uses modern Pythonic structures to efficiently request information. It features optional caching, is modular, and is easy to integrate.
Home-page: UNKNOWN
Author: TheOnlyWayUp
Author-email: thedarkdraconian@gmail.com
License: UNKNOWN
Keywords: async,aiohttp,better_than_sync,mcstalker,minecraft,server_scanning,api_wrapper,minecraft_server
Platform: UNKNOWN
Classifier: Development Status :: 5 - Production/Stable
Classifier: Intended Audience :: Developers
Classifier: Programming Language :: Python :: 3
Classifier: Operating System :: Unix
Classifier: Operating System :: MacOS :: MacOS X
Classifier: Operating System :: Microsoft :: Windows
